rest_api_response/__init__.py
rest_api_response/responses.py
rest_api_response-0.2.dist-info/LICENSE.txt
rest_api_response-0.2.dist-info/METADATA
rest_api_response-0.2.dist-info/WHEEL
rest_api_response-0.2.dist-info/top_level.txt
rest_api_response-0.2.dist-info/RECORD
