Metadata-Version: 2.1
Name: rest_api_response
Version: 0.2
Summary: A go-to production API response with an easy format for building APIs with Python.
Home-page: https://github.com/aybruhm/api-response
Author: Abraham 'Abram' Israel
Author-email: israelvictory87@gmail.com
License: MIT
Project-URL: Bug Tracker, https://github.com/aybruhm/api-response/issues
Keywords: api,response,custom api response
Classifier: Development Status :: 5 - Production/Stable
Classifier: Intended Audience :: Education
Classifier: Intended Audience :: Developers
Classifier: License :: OSI Approved :: MIT License
Classifier: Programming Language :: Python :: 3
Requires-Python: >=3
License-File: LICENSE.txt
